mod_dlm_server/main.py
mod_dlm_server/security_api.py
mod_dlm_server/apis/__init__.py
mod_dlm_server/apis/default_api.py
mod_dlm_server/apis/default_api_base.py
mod_dlm_server/impl/__init__.py
mod_dlm_server/models/__init__.py
mod_dlm_server/models/element_create.py
mod_dlm_server/models/extra_models.py
mod_dlm_server/models/installation_and_connectivity.py
mod_dlm_server/models/prefab_element.py
mod_dlm_server/models/prefab_element_aesthetic_and_customization_options.py
mod_dlm_server/models/prefab_element_bounding_box.py
mod_dlm_server/models/prefab_element_dimensional.py
mod_dlm_server/models/prefab_element_dimensional_width.py
mod_dlm_server/models/prefab_element_documentation_and_compliance.py
mod_dlm_server/models/prefab_element_documentation_and_compliance_certifications.py
mod_dlm_server/models/prefab_element_economic_factors.py
mod_dlm_server/models/prefab_element_lifecycle_and_maintenance.py
mod_dlm_server/models/prefab_element_material.py
mod_dlm_server/models/prefab_element_performance.py
mod_dlm_server/models/prefab_element_performance_acoustic_properties.py
mod_dlm_server/models/prefab_element_performance_fire_resistance.py
mod_dlm_server/models/prefab_element_product_category.py
mod_dlm_server/models/prefab_element_structural_properties.py
mod_dlm_server/models/prefab_element_structural_properties_deflection_limit.py
mod_dlm_server/models/prefab_element_structural_properties_load_bearing_capacity.py
mod_dlm_server/models/prefab_element_structural_properties_seismic_resistance.py
mod_dlm_server/models/prefab_element_structural_properties_wind_load_resistance.py
mod_dlm_server/models/prefab_element_version_metadata.py
mod_dlm_server/models/sustainability.py
mod_dlm_server/models/sustainability_circularity.py
mod_dlm_server/models/sustainability_environmental_impact.py
mod_dlm_server/models/sustainability_origin.py
mod_dlm_server-1.1.0.dist-info/licenses/LICENSE
mod_dlm_server-1.1.0.dist-info/METADATA
mod_dlm_server-1.1.0.dist-info/WHEEL
mod_dlm_server-1.1.0.dist-info/top_level.txt
mod_dlm_server-1.1.0.dist-info/RECORD
