Metadata-Version: 2.4
Name: mod_dlm_server
Version: 1.1.0
Summary: mod-dlm-server is an open-source REST server for storing and querying element data described using the mod-dlm domain-specific language (DSL).
Keywords: OpenAPI mod-dlm API
Classifier: Operating System :: OS Independent
Classifier: Programming Language :: Python :: 3
Classifier: Programming Language :: Python :: 3.7
License-File: LICENSE
Requires-Dist: fastapi[all]
Dynamic: license-file
